[
	{
		"name": "RED",
		"hp": 10,
		"reward": 1,
		"serial": 10,
		"img": "01.png",
		"background": "01.webp",
		"demage": 1
	},
	{
		"name": "RED",
		"hp": 10,
		"reward": 1,
		"serial": 15,
		"img": "01.png",
		"background": "01.webp",
		"demage": 1
	},
	{
		"name": "BLUE",
		"hp": 12,
		"reward": 2,
		"serial": 10,
		"img": "02.png",
		"background": "02.webp",
		"demage": 2
	},
	{
		"name": "BLUE",
		"hp": 12,
		"reward": 2,
		"serial": 15,
		"img": "02.png",
		"background": "02.webp",
		"demage": 2
	},
	{
		"name": "GREEN",
		"hp": 15,
		"reward": 4,
		"serial": 12,
		"img": "03.png",
		"background": "03.webp",
		"demage": 4
	},
	{
		"name": "GREEN",
		"hp": 15,
		"reward": 4,
		"serial": 15,
		"img": "03.png",
		"background": "03.webp",
		"demage": 4
	},
	{
		"name": "GREEN",
		"hp": 15,
		"reward": 4,
		"serial": 20,
		"img": "03.png",
		"background": "03.webp",
		"demage": 4
	},
	{
		"name": "GREEN",
		"hp": 15,
		"reward": 4,
		"serial": 25,
		"img": "03.png",
		"background": "03.webp",
		"demage": 4
	},
	{
		"name": "YELLOW",
		"hp": 20,
		"reward": 7,
		"serial": 20,
		"img": "04.png",
		"background": "04.webp",
		"demage": 8
	},
	{
		"name": "YELLOW",
		"hp": 20,
		"reward": 7,
		"serial": 25,
		"img": "04.png",
		"background": "04.webp",
		"demage": 8
	},
	{
		"name": "YELLOW",
		"hp": 20,
		"reward": 7,
		"serial": 30,
		"img": "04.png",
		"background": "04.webp",
		"demage": 8
	},
	{
		"name": "YELLOW",
		"hp": 20,
		"reward": 7,
		"serial": 35,
		"img": "04.png",
		"background": "04.webp",
		"demage": 8
	},
	{
		"name": "PINK",
		"hp": 30,
		"reward": 10,
		"serial": 20,
		"img": "05.png",
		"background": "05.webp",
		"demage": 16
	},
	{
		"name": "PINK",
		"hp": 30,
		"reward": 10,
		"serial": 25,
		"img": "05.png",
		"background": "05.webp"
	},
	{
		"name": "PINK",
		"hp": 30,
		"reward": 10,
		"serial": 30,
		"img": "05.png",
		"background": "05.webp",
		"demage": 16
	},
	{
		"name": "PINK",
		"hp": 30,
		"reward": 10,
		"serial": 40,
		"img": "05.png",
		"background": "05.webp",
		"demage": 16
	},
	{
		"name": "PINK",
		"hp": 30,
		"reward": 10,
		"serial": 45,
		"img": "05.png",
		"background": "05.webp",
		"demage": 16
	},
	{
		"name": "PURPLE",
		"hp": 50,
		"reward": 15,
		"serial": 25,
		"img": "06.png",
		"background": "06.webp",
		"demage": 32
	},
	{
		"name": "PURPLE",
		"hp": 50,
		"reward": 15,
		"serial": 30,
		"img": "06.png",
		"background": "06.webp"
	},
	{
		"name": "PURPLE",
		"hp": 50,
		"reward": 15,
		"serial": 35,
		"img": "06.png",
		"background": "06.webp",
		"demage": 32
	},
	{
		"name": "PURPLE",
		"hp": 50,
		"reward": 15,
		"serial": 40,
		"img": "06.png",
		"background": "06.webp",
		"demage": 32
	},
	{
		"name": "PURPLE",
		"hp": 50,
		"reward": 15,
		"serial": 45,
		"img": "06.png",
		"background": "06.webp",
		"demage": 32
	},
	{
		"name": "TIGER",
		"hp": 70,
		"reward": 30,
		"serial": 25,
		"img": "07.png",
		"background": "07.webp",
		"demage": 64
	},
	{
		"name": "TIGER",
		"hp": 70,
		"reward": 30,
		"serial": 30,
		"img": "07.png",
		"background": "07.webp",
		"demage": 64
	},
	{
		"name": "TIGER",
		"hp": 70,
		"reward": 30,
		"serial": 35,
		"img": "07.png",
		"background": "07.webp",
		"demage": 64
	},
	{
		"name": "TIGER",
		"hp": 70,
		"reward": 30,
		"serial": 40,
		"img": "07.png",
		"background": "07.webp",
		"demage": 64
	},
	{
		"name": "TIGER",
		"hp": 70,
		"reward": 30,
		"serial": 40,
		"img": "07.png",
		"background": "07.webp",
		"demage": 64
	},
	{
		"name": "TIGER",
		"hp": 70,
		"reward": 30,
		"serial": 50,
		"img": "07.png",
		"background": "07.webp",
		"demage": 64
	},
	{
		"name": "LGBT",
		"hp": 100,
		"reward": 50,
		"serial": 30,
		"img": "08.png",
		"background": "08.webp",
		"demage": 150
	},
	{
		"name": "LGBT",
		"hp": 100,
		"reward": 50,
		"serial": 35,
		"img": "08.png",
		"background": "08.webp",
		"demage": 150
	},
	{
		"name": "LGBT",
		"hp": 100,
		"reward": 50,
		"serial": 40,
		"img": "08.png",
		"background": "08.webp",
		"demage": 150
	},
	{
		"name": "LGBT",
		"hp": 100,
		"reward": 50,
		"serial": 50,
		"img": "08.png",
		"background": "08.webp",
		"demage": 150
	},
	{
		"name": "LGBT",
		"hp": 100,
		"reward": 50,
		"serial": 20,
		"img": "08.png",
		"background": "08.webp",
		"demage": 150
	},
	{
		"name": "LGBT",
		"hp": 100,
		"reward": 50,
		"serial": 15,
		"img": "08.png",
		"background": "08.webp",
		"demage": 150
	},
	{
		"name": "RHYNO",
		"hp": 200,
		"reward": 80,
		"serial": 10,
		"img": "09.png",
		"background": "09.webp",
		"demage": 500
	},
	{
		"name": "RHYNO",
		"hp": 200,
		"reward": 80,
		"serial": 20,
		"img": "09.png",
		"background": "09.webp",
		"demage": 500
	},
	{
		"name": "RHYNO",
		"hp": 200,
		"reward": 80,
		"serial": 25,
		"img": "09.png",
		"background": "09.webp",
		"demage": 500
	},
	{
		"name": "RHYNO",
		"hp": 200,
		"reward": 80,
		"serial": 40,
		"img": "09.png",
		"background": "09.webp",
		"demage": 500
	},
	{
		"name": "RHYNO",
		"hp": 200,
		"reward": 80,
		"serial": 15,
		"img": "09.png",
		"background": "09.webp",
		"demage": 500
	},
	{
		"name": "RHYNO",
		"hp": 200,
		"reward": 80,
		"serial": 5,
		"img": "09.png",
		"background": "09.webp",
		"demage": 500
	},
	{
		"name": "HIVE",
		"hp": 300,
		"reward": 100,
		"serial": 10,
		"img": "10.png",
		"background": "10.webp",
		"demage": 1000
	},
	{
		"name": "HIVE",
		"hp": 300,
		"reward": 100,
		"serial": 15,
		"img": "10.png",
		"background": "10.webp",
		"demage": 1000
	},
	{
		"name": "HIVE",
		"hp": 300,
		"reward": 100,
		"serial": 25,
		"img": "10.png",
		"background": "10.webp",
		"demage": 1000
	},
	{
		"name": "HIVE",
		"hp": 300,
		"reward": 100,
		"serial": 40,
		"img": "10.png",
		"background": "10.webp",
		"demage": 1000
	},
	{
		"name": "HIVE",
		"hp": 300,
		"reward": 100,
		"serial": 20,
		"img": "10.png",
		"background": "10.webp",
		"demage": 1000
	},
	{
		"name": "HIVE",
		"hp": 300,
		"reward": 100,
		"serial": 25,
		"img": "10.png",
		"background": "10.webp",
		"demage": 1000
	},
	{
		"name": "WHALE",
		"hp": 1000,
		"reward": 500,
		"serial": 5,
		"img": "11.webp",
		"background": "11.webp",
		"demage": 1000
	},
	{
		"name": "WHALE",
		"hp": 1000,
		"reward": 500,
		"serial": 7,
		"img": "11.webp",
		"background": "11.webp",
		"demage": 5000
	},
	{
		"name": "WHALE",
		"hp": 1000,
		"reward": 500,
		"serial": 9,
		"img": "11.webp",
		"background": "11.webp",
		"demage": 5000
	},
	{
		"name": "WHALE",
		"hp": 1000,
		"reward": 500,
		"serial": 4,
		"img": "11.webp",
		"background": "11.webp",
		"demage": 5000
	},
	{
		"name": "WHALE",
		"hp": 1000,
		"reward": 500,
		"serial": 12,
		"img": "11.webp",
		"background": "11.webp",
		"demage": 5000
	},
	{
		"name": "AIRBUS",
		"hp": 5000,
		"reward": 3000,
		"serial": 5,
		"img": "12.webp",
		"background": "12.webp",
		"demage": 10000
	},
	{
		"name": "AIRBUS",
		"hp": 5000,
		"reward": 3000,
		"serial": 7,
		"img": "12.webp",
		"background": "12.webp",
		"demage": 10000
	},
	{
		"name": "AIRBUS",
		"hp": 5000,
		"reward": 3000,
		"serial": 10,
		"img": "12.webp",
		"background": "12.webp",
		"demage": 10000
	},
	{
		"name": "AIRBUS",
		"hp": 5000,
		"reward": 3000,
		"serial": 15,
		"img": "12.webp",
		"background": "12.webp",
		"demage": 10000
	},
	{
		"name": "AIRBUS",
		"hp": 5000,
		"reward": 3000,
		"serial": 17,
		"img": "12.webp",
		"background": "12.webp",
		"demage": 10000
	},
	{
		"name": "POISON",
		"hp": 10000,
		"reward": 10000,
		"serial": 5,
		"img": "13.webp",
		"background": "13.webp",
		"demage": 20000
	},
	{
		"name": "POISON",
		"hp": 10000,
		"reward": 10000,
		"serial": 7,
		"img": "13.webp",
		"background": "13.webp",
		"demage": 20000
	},
	{
		"name": "POISON",
		"hp": 10000,
		"reward": 10000,
		"serial": 3,
		"img": "13.webp",
		"background": "13.webp",
		"demage": 20000
	},
	{
		"name": "POISON",
		"hp": 10000,
		"reward": 10000,
		"serial": 2,
		"img": "13.webp",
		"background": "13.webp",
		"demage": 20000
	},
	{
		"name": "POISON",
		"hp": 10000,
		"reward": 10000,
		"serial": 3,
		"img": "13.webp",
		"background": "13.webp",
		"demage": 20000
	},
	{
		"name": "POISON",
		"hp": 10000,
		"reward": 10000,
		"serial": 6,
		"img": "13.webp",
		"background": "13.webp",
		"demage": 20000
	},
	{
		"name": "POISON",
		"hp": 10000,
		"reward": 10000,
		"serial": 10,
		"img": "13.webp",
		"background": "13.webp",
		"demage": 20000
	},
	{
		"name": "TURBO",
		"hp": 100000,
		"reward": 50000,
		"serial": 3,
		"img": "15.webp",
		"background": "15.webp",
		"demage": 50000
	},
	{
		"name": "TURBO",
		"hp": 100000,
		"reward": 50000,
		"serial": 5,
		"img": "15.webp",
		"background": "15.webp",
		"demage": 50000
	},
	{
		"name": "TURBO",
		"hp": 100000,
		"reward": 50000,
		"serial": 3,
		"img": "15.webp",
		"background": "15.webp",
		"demage": 50000
	},
	{
		"name": "TURBO",
		"hp": 100000,
		"reward": 50000,
		"serial": 10,
		"img": "15.webp",
		"background": "15.webp",
		"demage": 50000
	},
	{
		"name": "TURBO",
		"hp": 100000,
		"reward": 50000,
		"serial": 6,
		"img": "15.webp",
		"background": "15.webp",
		"demage": 50000
	},
	{
		"name": "DEATH",
		"hp": 1000000,
		"reward": 100000,
		"serial": 3,
		"img": "16.webp",
		"background": "16.webp",
		"demage": 100000
	},
	{
		"name": "DEATH",
		"hp": 1000000,
		"reward": 100000,
		"serial": 5,
		"img": "16.webp",
		"background": "16.webp",
		"demage": 100000
	},
	{
		"name": "DEATH",
		"hp": 1000000,
		"reward": 100000,
		"serial": 4,
		"img": "16.webp",
		"background": "16.webp",
		"demage": 100000
	},
	{
		"name": "DEATH",
		"hp": 1000000,
		"reward": 100000,
		"serial": 2,
		"img": "16.webp",
		"background": "16.webp",
		"demage": 100000
	},
	{
		"name": "RAMPAGE",
		"hp": 2000000,
		"reward": 200000,
		"serial": 1,
		"img": "17.webp",
		"background": "17.webp",
		"demage": 500000
	},
	{
		"name": "RAMPAGE",
		"hp": 2000000,
		"reward": 200000,
		"serial": 3,
		"img": "17.webp",
		"background": "17.webp",
		"demage": 500000
	},
	{
		"name": "RAMPAGE",
		"hp": 2000000,
		"reward": 200000,
		"serial": 2,
		"img": "17.webp",
		"background": "17.webp",
		"demage": 500000
	},
	{
		"name": "RAMPAGE",
		"hp": 2000000,
		"reward": 200000,
		"serial": 4,
		"img": "17.webp",
		"background": "17.webp",
		"demage": 500000
	},
	{
		"name": "DOOM",
		"hp": 3000000,
		"reward": 500000,
		"serial": 4,
		"img": "18.webp",
		"background": "18.webp",
		"demage": 1000000
	},
	{
		"name": "DOOM",
		"hp": 3000000,
		"reward": 500000,
		"serial": 4,
		"img": "18.webp",
		"background": "18.webp",
		"demage": 1000000
	},
	{
		"name": "DOOM",
		"hp": 3000000,
		"reward": 500000,
		"serial": 4,
		"img": "18.webp",
		"background": "18.webp",
		"demage": 1000000
	},
	{
		"name": "DOOM",
		"hp": 3000000,
		"reward": 500000,
		"serial": 4,
		"img": "18.webp",
		"background": "18.webp",
		"demage": 1000000
	},
	{
		"name": "EVANGELION",
		"hp": 10000000,
		"reward": 10000000,
		"serial": 1,
		"img": "19.webp",
		"background": "19.webp",
		"demage": 5000000
	}
]
